MANIFEST.in
README.md
requirements.txt
setup.py
calm/__init__.py
calm/codec.py
calm/core.py
calm/ex.py
calm/service.py
calm/testing.py
calm.egg-info/PKG-INFO
calm.egg-info/SOURCES.txt
calm.egg-info/dependency_links.txt
calm.egg-info/requires.txt
calm.egg-info/top_level.txt