Metadata-Version: 1.1
Name: calm
Version: 0.1.4
Summary: It is always Calm before a Tornado!
Home-page: http://calm.n9co.de
Author: Bagrat Aznauryan
Author-email: bagrat@aznauryan.org
License: MIT
Keywords: tornado rest restful api framework
Platform: UNKNOWN
Classifier: Development Status :: 3 - Alpha
Classifier: Intended Audience :: Developers
Classifier: Intended Audience :: Information Technology
Classifier: License :: OSI Approved :: MIT License
Classifier: Programming Language :: Python :: 3.5
Classifier: Topic :: Internet :: WWW/HTTP
Classifier: Topic :: Internet :: WWW/HTTP :: HTTP Servers
Classifier: Topic :: Software Development
Classifier: Topic :: Software Development :: Libraries
Classifier: Topic :: Software Development :: Libraries :: Application Frameworks
